PythonIota/__init__.py
PythonIota-0.0.2.dist-info/LICENSE.txt
PythonIota-0.0.2.dist-info/METADATA
PythonIota-0.0.2.dist-info/WHEEL
PythonIota-0.0.2.dist-info/top_level.txt
PythonIota-0.0.2.dist-info/RECORD
