Metadata-Version: 2.1
Name: PythonIota
Version: 0.0.2
Summary: PythonIota may be an imitation of iota() function in Go,C++ etc.
Author: Equinox
Classifier: Programming Language :: Python :: 3
Classifier: License :: OSI Approved :: MIT License
Classifier: Operating System :: OS Independent
Requires-Python: >=3.6
License-File: LICENSE.txt
